linux_desktop_mcp/__init__.py
linux_desktop_mcp/atspi_bridge.py
linux_desktop_mcp/detection.py
linux_desktop_mcp/input_backends.py
linux_desktop_mcp/overlay.py
linux_desktop_mcp/references.py
linux_desktop_mcp/server.py
linux_desktop_mcp/window_discovery.py
linux_desktop_mcp/window_manager.py
linux_desktop_mcp-0.1.0.dist-info/METADATA
linux_desktop_mcp-0.1.0.dist-info/WHEEL
linux_desktop_mcp-0.1.0.dist-info/entry_points.txt
linux_desktop_mcp-0.1.0.dist-info/licenses/LICENSE
linux_desktop_mcp-0.1.0.dist-info/RECORD
