Metadata-Version: 2.4
Name: linux-desktop-mcp
Version: 0.1.0
Summary: MCP server for Linux desktop automation using AT-SPI2
Author: Austin Beck
License-Expression: MIT
License-File: LICENSE
Keywords: accessibility,at-spi,automation,desktop,linux,mcp
Classifier: Development Status :: 3 - Alpha
Classifier: Environment :: Console
Classifier: Intended Audience :: Developers
Classifier: License :: OSI Approved :: MIT License
Classifier: Operating System :: POSIX :: Linux
Classifier: Programming Language :: Python :: 3
Classifier: Programming Language :: Python :: 3.10
Classifier: Programming Language :: Python :: 3.11
Classifier: Programming Language :: Python :: 3.12
Classifier: Topic :: Desktop Environment
Classifier: Topic :: Software Development :: Libraries :: Python Modules
Requires-Python: >=3.10
Requires-Dist: mcp>=1.0.0
Requires-Dist: pygobject>=3.42.0
Provides-Extra: dev
Requires-Dist: pytest-asyncio>=0.21.0; extra == 'dev'
Requires-Dist: pytest>=7.0.0; extra == 'dev'
Requires-Dist: ruff>=0.1.0; extra == 'dev'
Provides-Extra: ocr
Requires-Dist: pillow>=10.0.0; extra == 'ocr'
Requires-Dist: pytesseract>=0.3.10; extra == 'ocr'
